barkr/__init__.py
barkr/connections/__init__.py
barkr/connections/base.py
barkr/connections/bluesky.py
barkr/connections/discord.py
barkr/connections/mastodon.py
barkr/connections/mastodon_activity_bot.py
barkr/connections/rss.py
barkr/connections/telegram.py
barkr/connections/twitter.py
barkr/main.py
barkr/models/__init__.py
barkr/models/media.py
barkr/models/message.py
barkr/models/message_allowed_replies.py
barkr/models/message_metadata.py
barkr/models/message_type.py
barkr/models/message_visibility.py
barkr/py.typed
barkr/utils.py
barkr-0.11.1.dist-info/METADATA
barkr-0.11.1.dist-info/WHEEL
barkr-0.11.1.dist-info/licenses/LICENSE
barkr-0.11.1.dist-info/RECORD
