Metadata-Version: 2.4
Name: barkr
Version: 0.11.1
Summary: Yet another cross-posting tool in Python
License-File: LICENSE
Keywords: python,cli,social media,crossposting,mastodon,fediverse,twitter,bluesky
Author: Andrés Ignacio Torres
Author-email: dev@aitorres.com
Requires-Python: >=3.10.0,<3.15
Classifier: Development Status :: 4 - Beta
Classifier: Environment :: Console
Classifier: Intended Audience :: End Users/Desktop
Classifier: License :: OSI Approved :: GNU Affero General Public License v3
Classifier: Natural Language :: English
Classifier: Operating System :: OS Independent
Classifier: Programming Language :: Python :: 3
Classifier: Programming Language :: Python :: 3.10
Classifier: Programming Language :: Python :: 3.11
Classifier: Programming Language :: Python :: 3.12
Classifier: Programming Language :: Python :: 3.13
Classifier: Programming Language :: Python :: 3.14
Classifier: Topic :: Communications
Classifier: Topic :: Internet
Requires-Dist: atproto (>=0.0.65,<0.0.66)
Requires-Dist: beautifulsoup4 (>=4.14.3,<5.0.0)
Requires-Dist: discord-py (>=2.6.4,<3.0.0)
Requires-Dist: feedparser (>=6.0.12,<7.0.0)
Requires-Dist: lxml (>=6.0.2,<7.0.0)
Requires-Dist: mastodon-py (>=2.1.4,<3.0.0)
Requires-Dist: pillow (>=12.1.0,<13.0.0)
Requires-Dist: python-telegram-bot (>=22.6,<23.0)
Requires-Dist: requests (>=2.32.5,<3.0.0)
Requires-Dist: tweepy (>=4.16.0,<5.0.0)
Project-URL: Bug Tracker, https://github.com/aitorres/barkr/issues
Project-URL: Change Log, https://github.com/aitorres/barkr/blob/main/CHANGELOG.md
Project-URL: Repository, https://github.com/aitorres/barkr
